datacommons_mcp/__init__.py
datacommons_mcp/_constrained_vars.py
datacommons_mcp/cache.py
datacommons_mcp/cli.py
datacommons_mcp/clients.py
datacommons_mcp/exceptions.py
datacommons_mcp/server.py
datacommons_mcp/services.py
datacommons_mcp/settings.py
datacommons_mcp/topics.py
datacommons_mcp/utils.py
datacommons_mcp/version.py
datacommons_mcp/data/topics/sdg_topic_cache.json
datacommons_mcp/data/topics/topic_cache.json
datacommons_mcp/data_models/__init__.py
datacommons_mcp/data_models/charts.py
datacommons_mcp/data_models/enums.py
datacommons_mcp/data_models/observations.py
datacommons_mcp/data_models/search.py
datacommons_mcp/data_models/settings.py
un_datacommons_mcp-1.0.1.dist-info/METADATA
un_datacommons_mcp-1.0.1.dist-info/WHEEL
un_datacommons_mcp-1.0.1.dist-info/entry_points.txt
un_datacommons_mcp-1.0.1.dist-info/top_level.txt
un_datacommons_mcp-1.0.1.dist-info/RECORD
