Metadata-Version: 2.4
Name: un-datacommons-mcp
Version: 1.0.1
Summary: Data Commons MCP server.
Project-URL: Homepage, https://github.com/datacommonsorg/agent-toolkit
Requires-Python: <3.13,>=3.11
Requires-Dist: fastapi
Requires-Dist: uvicorn
Requires-Dist: fastmcp
Requires-Dist: requests
Requires-Dist: datacommons-client
Requires-Dist: pydantic>=2.11.7
Requires-Dist: pydantic-settings
Requires-Dist: python-dateutil>=2.9.0.post0
